tessdb_dao-1.0.0.dist-info/licenses/LICENSE
tessdbdao/__init__.py
tessdbdao/_version.py
tessdbdao/asyncio.py
tessdbdao/constants.py
tessdbdao/model.py
tessdbdao/noasync.py
tessdbdao/cli/__init__.py
tessdbdao/cli/aiopopulate.py
tessdbdao/cli/aioschema.py
tessdbdao/cli/populate.py
tessdbdao/cli/schema.py
tessdbdao/cli/util/__init__.py
tessdbdao/cli/util/parser.py
tessdb_dao-1.0.0.dist-info/METADATA
tessdb_dao-1.0.0.dist-info/WHEEL
tessdb_dao-1.0.0.dist-info/entry_points.txt
tessdb_dao-1.0.0.dist-info/top_level.txt
tessdb_dao-1.0.0.dist-info/RECORD
