Metadata-Version: 2.4
Name: tessdb-dao
Version: 1.0.0
Summary: Database independant SQLAlchemy Data Access Object layer for TESS database
Author-email: Rafael González <rafael08@ucm.es>
Project-URL: Homepage, https://foundation.stars4all.eu
Project-URL: Repository, https://github.com/astrorafael/tessdb-dao.git
Classifier: Programming Language :: Python :: 3.9
Classifier: Programming Language :: Python :: 3.10
Classifier: Programming Language :: Python :: 3.11
Classifier: Programming Language :: Python :: 3.12
Classifier: Development Status :: 4 - Beta
Classifier: Environment :: Console
Classifier: Environment :: No Input/Output (Daemon)
Classifier: Intended Audience :: Science/Research
Classifier: License :: OSI Approved :: MIT License
Classifier: Operating System :: POSIX :: Linux
Classifier: Topic :: Scientific/Engineering :: Astronomy
Classifier: Topic :: Scientific/Engineering :: Atmospheric Science
Requires-Python: >=3.12
License-File: LICENSE
Requires-Dist: SQLAlchemy[asyncio]>=2.0
Requires-Dist: alembic>=1.15
Requires-Dist: aiosqlite>=0.21
Requires-Dist: lica[aiosqlalchemy]>=2.0
Dynamic: license-file
